public_apis_mcp/__init__.py
public_apis_mcp/__main__.py
public_apis_mcp/embeddings.py
public_apis_mcp/resources.py
public_apis_mcp/server.py
public_apis_mcp/tools.py
public_apis_mcp/types.py
public_apis_mcp/datastore/index.json
public_apis_mcp/datastore/index.npz
public_apis_mcp-0.1.0.dist-info/licenses/LICENSE
public_apis_mcp-0.1.0.dist-info/METADATA
public_apis_mcp-0.1.0.dist-info/WHEEL
public_apis_mcp-0.1.0.dist-info/entry_points.txt
public_apis_mcp-0.1.0.dist-info/top_level.txt
public_apis_mcp-0.1.0.dist-info/RECORD
