Metadata-Version: 2.4
Name: public-apis-mcp
Version: 0.1.0
Summary: MCP server exposing a catalog of free APIs with embedding-based lookups
Author-email: Alexander Galea <alex@galea.dev>
License: MIT License
Project-URL: Homepage, https://pypi.org/project/public-apis-mcp/
Project-URL: Repository, https://github.com/zazencodes/public-apis-mcp
Project-URL: Changelog, https://github.com/zazencodes/public-apis-mcp/blob/main/CHANGELOG.md
Keywords: mcp,model context protocol,public,free,api,apis
Classifier: Programming Language :: Python :: 3
Classifier: Programming Language :: Python :: 3 :: Only
Classifier: License :: OSI Approved :: MIT License
Classifier: Operating System :: OS Independent
Classifier: Typing :: Typed
Requires-Python: >=3.10
License-File: LICENSE
Requires-Dist: fastmcp>=2.10
Requires-Dist: pydantic>=2
Requires-Dist: numpy>=1.24
Requires-Dist: fastembed>=0.3.2
Dynamic: license-file
